{
    "T18Eval-00001": {
        "map": 0.32354389797828714,
        "recip_rank": 1.0,
        "ndcg_cut_5": 0.6985436835905778,
        "ndcg_cut_10": 0.634989785622961,
        "ndcg_cut_15": 0.5919044439207799,
        "ndcg_cut_20": 0.5919044439207799,
        "ndcg_cut_30": 0.5919044439207799,
        "ndcg_cut_100": 0.6242589796740057,
        "ndcg_cut_200": 0.6242589796740057,
        "ndcg_cut_500": 0.6449427329848522,
        "ndcg_cut_1000": 0.6449427329848522,
        "success_1": 1.0,
        "success_5": 1.0,
        "success_10": 1.0,
        "count_relevant_top5": 4
    },
    "T18Eval-00002": {
        "map": 0.3280542484525538,
        "recip_rank": 1.0,
        "ndcg_cut_5": 0.5531464700081437,
        "ndcg_cut_10": 0.6012058024381003,
        "ndcg_cut_15": 0.6012058024381003,
        "ndcg_cut_20": 0.6012058024381003,
        "ndcg_cut_30": 0.6603544853307214,
        "ndcg_cut_100": 0.674739888884591,
        "ndcg_cut_200": 0.674739888884591,
        "ndcg_cut_500": 0.6866464486211287,
        "ndcg_cut_1000": 0.6972558921801095,
        "success_1": 1.0,
        "success_5": 1.0,
        "success_10": 1.0,
        "count_relevant_top5": 2
    },
    "T18Eval-00003": {
        "map": 0.39119303635432673,
        "recip_rank": 1.0,
        "ndcg_cut_5": 0.4692787260227565,
        "ndcg_cut_10": 0.4692787260227565,
        "ndcg_cut_15": 0.5960957428551501,
        "ndcg_cut_20": 0.5960957428551501,
        "ndcg_cut_30": 0.5960957428551501,
        "ndcg_cut_100": 0.5960957428551501,
        "ndcg_cut_200": 0.5960957428551501,
        "ndcg_cut_500": 0.649636598664008,
        "ndcg_cut_1000": 0.649636598664008,
        "success_1": 1.0,
        "success_5": 1.0,
        "success_10": 1.0,
        "count_relevant_top5": 1
    },
    "T18Eval-00004": {
        "map": 0.147535662578268,
        "recip_rank": 0.5,
        "ndcg_cut_5": 0.24090885754831726,
        "ndcg_cut_10": 0.18028843738337746,
        "ndcg_cut_15": 0.18028843738337746,
        "ndcg_cut_20": 0.18028843738337746,
        "ndcg_cut_30": 0.19828792961925795,
        "ndcg_cut_100": 0.28246732543852865,
        "ndcg_cut_200": 0.2946746165377547,
        "ndcg_cut_500": 0.2946746165377547,
        "ndcg_cut_1000": 0.2946746165377547,
        "success_1": 0.0,
        "success_5": 1.0,
        "success_10": 1.0,
        "count_relevant_top5": 2
    },
    "T18Eval-00005": {
        "map": 0.1252266753096144,
        "recip_rank": 1.0,
        "ndcg_cut_5": 0.5531464700081437,
        "ndcg_cut_10": 0.35895421017163465,
        "ndcg_cut_15": 0.2782516503241438,
        "ndcg_cut_20": 0.2607684565272652,
        "ndcg_cut_30": 0.2853542642272463,
        "ndcg_cut_100": 0.361288962133769,
        "ndcg_cut_200": 0.4797700221347741,
        "ndcg_cut_500": 0.5106339130494968,
        "ndcg_cut_1000": 0.5106339130494968,
        "success_1": 1.0,
        "success_5": 1.0,
        "success_10": 1.0,
        "count_relevant_top5": 2
    },
    "T18Eval-00006": {
        "map": 0.15795077578285982,
        "recip_rank": 1.0,
        "ndcg_cut_5": 0.20803518926146267,
        "ndcg_cut_10": 0.17034964791167806,
        "ndcg_cut_15": 0.16511891914140736,
        "ndcg_cut_20": 0.16511891914140736,
        "ndcg_cut_30": 0.16511891914140736,
        "ndcg_cut_100": 0.16511891914140736,
        "ndcg_cut_200": 0.16511891914140736,
        "ndcg_cut_500": 0.24605911060690902,
        "ndcg_cut_1000": 0.2582486064400322,
        "success_1": 1.0,
        "success_5": 1.0,
        "success_10": 1.0,
        "count_relevant_top5": 2
    },
    "T18Eval-00007": {
        "map": 0.04099943712565344,
        "recip_rank": 0.04,
        "ndcg_cut_5": 0.0,
        "ndcg_cut_10": 0.0,
        "ndcg_cut_15": 0.0,
        "ndcg_cut_20": 0.0,
        "ndcg_cut_30": 0.04299238377896123,
        "ndcg_cut_100": 0.20680251019089044,
        "ndcg_cut_200": 0.2356715256612039,
        "ndcg_cut_500": 0.2356715256612039,
        "ndcg_cut_1000": 0.2356715256612039,
        "success_1": 0.0,
        "success_5": 0.0,
        "success_10": 0.0,
        "count_relevant_top5": 0
    },
    "T18Eval-00008": {
        "map": 0.1111111111111111,
        "recip_rank": 0.3333333333333333,
        "ndcg_cut_5": 0.12103812696590094,
        "ndcg_cut_10": 0.12103812696590094,
        "ndcg_cut_15": 0.12103812696590094,
        "ndcg_cut_20": 0.12103812696590094,
        "ndcg_cut_30": 0.12103812696590094,
        "ndcg_cut_100": 0.12103812696590094,
        "ndcg_cut_200": 0.12103812696590094,
        "ndcg_cut_500": 0.12103812696590094,
        "ndcg_cut_1000": 0.12103812696590094,
        "success_1": 0.0,
        "success_5": 1.0,
        "success_10": 1.0,
        "count_relevant_top5": 1
    },
    "T18Eval-00009": {
        "map": 0.0051386266976228894,
        "recip_rank": 0.009009009009009009,
        "ndcg_cut_5": 0.0,
        "ndcg_cut_10": 0.0,
        "ndcg_cut_15": 0.0,
        "ndcg_cut_20": 0.0,
        "ndcg_cut_30": 0.0,
        "ndcg_cut_100": 0.0,
        "ndcg_cut_200": 0.03880002379458108,
        "ndcg_cut_500": 0.10717881356887006,
        "ndcg_cut_1000": 0.10717881356887006,
        "success_1": 0.0,
        "success_5": 0.0,
        "success_10": 0.0,
        "count_relevant_top5": 0
    },
    "T18Eval-00010": {
        "map": 0.008995992451866667,
        "recip_rank": 0.01020408163265306,
        "ndcg_cut_5": 0.0,
        "ndcg_cut_10": 0.0,
        "ndcg_cut_15": 0.0,
        "ndcg_cut_20": 0.0,
        "ndcg_cut_30": 0.0,
        "ndcg_cut_100": 0.08391438641322622,
        "ndcg_cut_200": 0.10871901587313133,
        "ndcg_cut_500": 0.10871901587313133,
        "ndcg_cut_1000": 0.16986393029152705,
        "success_1": 0.0,
        "success_5": 0.0,
        "success_10": 0.0,
        "count_relevant_top5": 0
    },
    "T18Eval-00011": {
        "map": 0.28979037310142464,
        "recip_rank": 1.0,
        "ndcg_cut_5": 0.6164336326286644,
        "ndcg_cut_10": 0.4000232483092519,
        "ndcg_cut_15": 0.46141629391399847,
        "ndcg_cut_20": 0.5132278574591737,
        "ndcg_cut_30": 0.5132278574591737,
        "ndcg_cut_100": 0.5132278574591737,
        "ndcg_cut_200": 0.5762370137135733,
        "ndcg_cut_500": 0.6290013393200208,
        "ndcg_cut_1000": 0.6290013393200208,
        "success_1": 1.0,
        "success_5": 1.0,
        "success_10": 1.0,
        "count_relevant_top5": 3
    },
    "T18Eval-00012": {
        "map": 0.2328042328042328,
        "recip_rank": 0.3333333333333333,
        "ndcg_cut_5": 0.2781491965442198,
        "ndcg_cut_10": 0.4456116994035126,
        "ndcg_cut_15": 0.4456116994035126,
        "ndcg_cut_20": 0.4456116994035126,
        "ndcg_cut_30": 0.4871938590942605,
        "ndcg_cut_100": 0.4871938590942605,
        "ndcg_cut_200": 0.4871938590942605,
        "ndcg_cut_500": 0.4871938590942605,
        "ndcg_cut_1000": 0.4871938590942605,
        "success_1": 0.0,
        "success_5": 1.0,
        "success_10": 1.0,
        "count_relevant_top5": 1
    },
    "T18Eval-00013": {
        "map": 0.023156381193839917,
        "recip_rank": 0.09090909090909091,
        "ndcg_cut_5": 0.0,
        "ndcg_cut_10": 0.0,
        "ndcg_cut_15": 0.050496160768241476,
        "ndcg_cut_20": 0.04714250231732918,
        "ndcg_cut_30": 0.04544411205120112,
        "ndcg_cut_100": 0.10168601149271284,
        "ndcg_cut_200": 0.15293711420182327,
        "ndcg_cut_500": 0.20647735318255186,
        "ndcg_cut_1000": 0.2240713007621731,
        "success_1": 0.0,
        "success_5": 0.0,
        "success_10": 0.0,
        "count_relevant_top5": 0
    },
    "T18Eval-00014": {
        "map": 0.0,
        "recip_rank": 0.0,
        "ndcg_cut_5": 0.0,
        "ndcg_cut_10": 0.0,
        "ndcg_cut_15": 0.0,
        "ndcg_cut_20": 0.0,
        "ndcg_cut_30": 0.0,
        "ndcg_cut_100": 0.0,
        "ndcg_cut_200": 0.0,
        "ndcg_cut_500": 0.0,
        "ndcg_cut_1000": 0.0,
        "success_1": 0.0,
        "success_5": 0.0,
        "success_10": 0.0,
        "count_relevant_top5": 0
    },
    "T18Eval-00015": {
        "map": 0.31567900262131643,
        "recip_rank": 1.0,
        "ndcg_cut_5": 0.4336152549062219,
        "ndcg_cut_10": 0.5214599788685887,
        "ndcg_cut_15": 0.5214599788685887,
        "ndcg_cut_20": 0.5214599788685887,
        "ndcg_cut_30": 0.5214599788685887,
        "ndcg_cut_100": 0.5214599788685887,
        "ndcg_cut_200": 0.5214599788685887,
        "ndcg_cut_500": 0.5893299972140192,
        "ndcg_cut_1000": 0.5893299972140192,
        "success_1": 1.0,
        "success_5": 1.0,
        "success_10": 1.0,
        "count_relevant_top5": 2
    },
    "T18Eval-00016": {
        "map": 1.0,
        "recip_rank": 1.0,
        "ndcg_cut_5": 1.0,
        "ndcg_cut_10": 1.0,
        "ndcg_cut_15": 1.0,
        "ndcg_cut_20": 1.0,
        "ndcg_cut_30": 1.0,
        "ndcg_cut_100": 1.0,
        "ndcg_cut_200": 1.0,
        "ndcg_cut_500": 1.0,
        "ndcg_cut_1000": 1.0,
        "success_1": 1.0,
        "success_5": 1.0,
        "success_10": 1.0,
        "count_relevant_top5": 1
    },
    "T18Eval-00017": {
        "map": 0.0,
        "recip_rank": 0.0,
        "ndcg_cut_5": 0.0,
        "ndcg_cut_10": 0.0,
        "ndcg_cut_15": 0.0,
        "ndcg_cut_20": 0.0,
        "ndcg_cut_30": 0.0,
        "ndcg_cut_100": 0.0,
        "ndcg_cut_200": 0.0,
        "ndcg_cut_500": 0.0,
        "ndcg_cut_1000": 0.0,
        "success_1": 0.0,
        "success_5": 0.0,
        "success_10": 0.0,
        "count_relevant_top5": 0
    },
    "T18Eval-00018": {
        "map": 0.009696969696969697,
        "recip_rank": 0.030303030303030304,
        "ndcg_cut_5": 0.0,
        "ndcg_cut_10": 0.0,
        "ndcg_cut_15": 0.0,
        "ndcg_cut_20": 0.0,
        "ndcg_cut_30": 0.0,
        "ndcg_cut_100": 0.02726115757539818,
        "ndcg_cut_200": 0.08849826562224994,
        "ndcg_cut_500": 0.08849826562224994,
        "ndcg_cut_1000": 0.08849826562224994,
        "success_1": 0.0,
        "success_5": 0.0,
        "success_10": 0.0,
        "count_relevant_top5": 0
    },
    "T18Eval-00019": {
        "map": 0.2694189859966069,
        "recip_rank": 1.0,
        "ndcg_cut_5": 0.6018359199557124,
        "ndcg_cut_10": 0.5621735131316713,
        "ndcg_cut_15": 0.5027681042623274,
        "ndcg_cut_20": 0.5027681042623274,
        "ndcg_cut_30": 0.5533611531345841,
        "ndcg_cut_100": 0.5961807607109864,
        "ndcg_cut_200": 0.6076735037482266,
        "ndcg_cut_500": 0.6732902545326022,
        "ndcg_cut_1000": 0.6732902545326022,
        "success_1": 1.0,
        "success_5": 1.0,
        "success_10": 1.0,
        "count_relevant_top5": 3
    },
    "T18Eval-00020": {
        "map": 0.06258531931781858,
        "recip_rank": 0.3333333333333333,
        "ndcg_cut_5": 0.16958010263680803,
        "ndcg_cut_10": 0.1269082923178573,
        "ndcg_cut_15": 0.1269082923178573,
        "ndcg_cut_20": 0.1269082923178573,
        "ndcg_cut_30": 0.1269082923178573,
        "ndcg_cut_100": 0.18331885937717535,
        "ndcg_cut_200": 0.30360882664932637,
        "ndcg_cut_500": 0.3349927834745888,
        "ndcg_cut_1000": 0.34441418806194896,
        "success_1": 0.0,
        "success_5": 1.0,
        "success_10": 1.0,
        "count_relevant_top5": 1
    },
    "T18Eval-00021": {
        "map": 0.014398299564145787,
        "recip_rank": 0.013157894736842105,
        "ndcg_cut_5": 0.0,
        "ndcg_cut_10": 0.0,
        "ndcg_cut_15": 0.0,
        "ndcg_cut_20": 0.0,
        "ndcg_cut_30": 0.0,
        "ndcg_cut_100": 0.15163791863946646,
        "ndcg_cut_200": 0.15163791863946646,
        "ndcg_cut_500": 0.17898576286767062,
        "ndcg_cut_1000": 0.17898576286767062,
        "success_1": 0.0,
        "success_5": 0.0,
        "success_10": 0.0,
        "count_relevant_top5": 0
    },
    "T18Eval-00022": {
        "map": 0.18626908464550498,
        "recip_rank": 1.0,
        "ndcg_cut_5": 0.20208310829219417,
        "ndcg_cut_10": 0.18851327158341571,
        "ndcg_cut_15": 0.18851327158341571,
        "ndcg_cut_20": 0.18851327158341571,
        "ndcg_cut_30": 0.18851327158341571,
        "ndcg_cut_100": 0.21850550835987761,
        "ndcg_cut_200": 0.29921827449469096,
        "ndcg_cut_500": 0.29921827449469096,
        "ndcg_cut_1000": 0.29921827449469096,
        "success_1": 1.0,
        "success_5": 1.0,
        "success_10": 1.0,
        "count_relevant_top5": 1
    },
    "T18Eval-00023": {
        "map": 0.01553283741917943,
        "recip_rank": 0.04,
        "ndcg_cut_5": 0.0,
        "ndcg_cut_10": 0.0,
        "ndcg_cut_15": 0.0,
        "ndcg_cut_20": 0.0,
        "ndcg_cut_30": 0.062283347998148164,
        "ndcg_cut_100": 0.11590781720294302,
        "ndcg_cut_200": 0.15420774271709992,
        "ndcg_cut_500": 0.15420774271709992,
        "ndcg_cut_1000": 0.18626684350811598,
        "success_1": 0.0,
        "success_5": 0.0,
        "success_10": 0.0,
        "count_relevant_top5": 0
    },
    "T18Eval-00024": {
        "map": 0.1180995475113122,
        "recip_rank": 0.5,
        "ndcg_cut_5": 0.3047813445164083,
        "ndcg_cut_10": 0.3047813445164083,
        "ndcg_cut_15": 0.3047813445164083,
        "ndcg_cut_20": 0.3047813445164083,
        "ndcg_cut_30": 0.3386459383515648,
        "ndcg_cut_100": 0.3386459383515648,
        "ndcg_cut_200": 0.3386459383515648,
        "ndcg_cut_500": 0.35930461717415496,
        "ndcg_cut_1000": 0.35930461717415496,
        "success_1": 0.0,
        "success_5": 1.0,
        "success_10": 1.0,
        "count_relevant_top5": 1
    },
    "T18Eval-00025": {
        "map": 0.5,
        "recip_rank": 1.0,
        "ndcg_cut_5": 0.8262346571285599,
        "ndcg_cut_10": 0.8262346571285599,
        "ndcg_cut_15": 0.8262346571285599,
        "ndcg_cut_20": 0.8262346571285599,
        "ndcg_cut_30": 0.8262346571285599,
        "ndcg_cut_100": 0.8262346571285599,
        "ndcg_cut_200": 0.8262346571285599,
        "ndcg_cut_500": 0.8262346571285599,
        "ndcg_cut_1000": 0.8262346571285599,
        "success_1": 1.0,
        "success_5": 1.0,
        "success_10": 1.0,
        "count_relevant_top5": 1
    },
    "T18Eval-00026": {
        "map": 0.010638297872340425,
        "recip_rank": 0.010638297872340425,
        "ndcg_cut_5": 0.0,
        "ndcg_cut_10": 0.0,
        "ndcg_cut_15": 0.0,
        "ndcg_cut_20": 0.0,
        "ndcg_cut_30": 0.0,
        "ndcg_cut_100": 0.15221034671324338,
        "ndcg_cut_200": 0.15221034671324338,
        "ndcg_cut_500": 0.15221034671324338,
        "ndcg_cut_1000": 0.15221034671324338,
        "success_1": 0.0,
        "success_5": 0.0,
        "success_10": 0.0,
        "count_relevant_top5": 0
    },
    "T18Eval-00027": {
        "map": 0.3145198496447783,
        "recip_rank": 1.0,
        "ndcg_cut_5": 0.2499832284140636,
        "ndcg_cut_10": 0.2151680076745172,
        "ndcg_cut_15": 0.2151680076745172,
        "ndcg_cut_20": 0.2151680076745172,
        "ndcg_cut_30": 0.2151680076745172,
        "ndcg_cut_100": 0.2718504624314351,
        "ndcg_cut_200": 0.4071097628177953,
        "ndcg_cut_500": 0.41928065260067693,
        "ndcg_cut_1000": 0.41928065260067693,
        "success_1": 1.0,
        "success_5": 1.0,
        "success_10": 1.0,
        "count_relevant_top5": 3
    },
    "T18Eval-00028": {
        "map": 1.0,
        "recip_rank": 1.0,
        "ndcg_cut_5": 1.0,
        "ndcg_cut_10": 1.0,
        "ndcg_cut_15": 1.0,
        "ndcg_cut_20": 1.0,
        "ndcg_cut_30": 1.0,
        "ndcg_cut_100": 1.0,
        "ndcg_cut_200": 1.0,
        "ndcg_cut_500": 1.0,
        "ndcg_cut_1000": 1.0,
        "success_1": 1.0,
        "success_5": 1.0,
        "success_10": 1.0,
        "count_relevant_top5": 1
    },
    "T18Eval-00029": {
        "map": 0.18904257661956433,
        "recip_rank": 1.0,
        "ndcg_cut_5": 0.5087403079104241,
        "ndcg_cut_10": 0.3614316054247357,
        "ndcg_cut_15": 0.3461626474621854,
        "ndcg_cut_20": 0.4026219003706547,
        "ndcg_cut_30": 0.4026219003706547,
        "ndcg_cut_100": 0.464093856001976,
        "ndcg_cut_200": 0.5317209140634842,
        "ndcg_cut_500": 0.5497084382045865,
        "ndcg_cut_1000": 0.5497084382045865,
        "success_1": 1.0,
        "success_5": 1.0,
        "success_10": 1.0,
        "count_relevant_top5": 2
    },
    "T18Eval-00030": {
        "map": 0.010367416544857386,
        "recip_rank": 0.008,
        "ndcg_cut_5": 0.0,
        "ndcg_cut_10": 0.0,
        "ndcg_cut_15": 0.0,
        "ndcg_cut_20": 0.0,
        "ndcg_cut_30": 0.0,
        "ndcg_cut_100": 0.0,
        "ndcg_cut_200": 0.022915093694681803,
        "ndcg_cut_500": 0.11823135544584837,
        "ndcg_cut_1000": 0.18897338800184668,
        "success_1": 0.0,
        "success_5": 0.0,
        "success_10": 0.0,
        "count_relevant_top5": 0
    },
    "T18Eval-00031": {
        "map": 0.011842178075097895,
        "recip_rank": 0.016666666666666666,
        "ndcg_cut_5": 0.0,
        "ndcg_cut_10": 0.0,
        "ndcg_cut_15": 0.0,
        "ndcg_cut_20": 0.0,
        "ndcg_cut_30": 0.0,
        "ndcg_cut_100": 0.019798742315671723,
        "ndcg_cut_200": 0.05256057432989062,
        "ndcg_cut_500": 0.1264691979528252,
        "ndcg_cut_1000": 0.1264691979528252,
        "success_1": 0.0,
        "success_5": 0.0,
        "success_10": 0.0,
        "count_relevant_top5": 0
    },
    "T18Eval-00032": {
        "map": 0.014869384020161832,
        "recip_rank": 0.019230769230769232,
        "ndcg_cut_5": 0.0,
        "ndcg_cut_10": 0.0,
        "ndcg_cut_15": 0.0,
        "ndcg_cut_20": 0.0,
        "ndcg_cut_30": 0.0,
        "ndcg_cut_100": 0.07976063828103006,
        "ndcg_cut_200": 0.10239579449630418,
        "ndcg_cut_500": 0.20902476627943645,
        "ndcg_cut_1000": 0.20902476627943645,
        "success_1": 0.0,
        "success_5": 0.0,
        "success_10": 0.0,
        "count_relevant_top5": 0
    },
    "T18Eval-00033": {
        "map": 0.2222222222222222,
        "recip_rank": 0.3333333333333333,
        "ndcg_cut_5": 0.23463936301137825,
        "ndcg_cut_10": 0.4017998179775806,
        "ndcg_cut_15": 0.4017998179775806,
        "ndcg_cut_20": 0.4017998179775806,
        "ndcg_cut_30": 0.4017998179775806,
        "ndcg_cut_100": 0.4017998179775806,
        "ndcg_cut_200": 0.4017998179775806,
        "ndcg_cut_500": 0.4017998179775806,
        "ndcg_cut_1000": 0.4017998179775806,
        "success_1": 0.0,
        "success_5": 1.0,
        "success_10": 1.0,
        "count_relevant_top5": 1
    },
    "T18Eval-00034": {
        "map": 0.2643452798519386,
        "recip_rank": 1.0,
        "ndcg_cut_5": 0.6785815599127776,
        "ndcg_cut_10": 0.5745168941836284,
        "ndcg_cut_15": 0.5745168941836284,
        "ndcg_cut_20": 0.5745168941836284,
        "ndcg_cut_30": 0.5745168941836284,
        "ndcg_cut_100": 0.6153175982886206,
        "ndcg_cut_200": 0.7308990413551831,
        "ndcg_cut_500": 0.7308990413551831,
        "ndcg_cut_1000": 0.7308990413551831,
        "success_1": 1.0,
        "success_5": 1.0,
        "success_10": 1.0,
        "count_relevant_top5": 2
    },
    "T18Eval-00035": {
        "map": 0.27888692319032876,
        "recip_rank": 1.0,
        "ndcg_cut_5": 0.624105567784388,
        "ndcg_cut_10": 0.5696304094250093,
        "ndcg_cut_15": 0.5696304094250093,
        "ndcg_cut_20": 0.657497120287823,
        "ndcg_cut_30": 0.657497120287823,
        "ndcg_cut_100": 0.6821759175017024,
        "ndcg_cut_200": 0.6821759175017024,
        "ndcg_cut_500": 0.6962900036135672,
        "ndcg_cut_1000": 0.6962900036135672,
        "success_1": 1.0,
        "success_5": 1.0,
        "success_10": 1.0,
        "count_relevant_top5": 2
    },
    "T18Eval-00036": {
        "map": 0.19716615874111126,
        "recip_rank": 1.0,
        "ndcg_cut_5": 0.3716702184910473,
        "ndcg_cut_10": 0.4529278388468162,
        "ndcg_cut_15": 0.4529278388468162,
        "ndcg_cut_20": 0.4529278388468162,
        "ndcg_cut_30": 0.4529278388468162,
        "ndcg_cut_100": 0.48947464474042224,
        "ndcg_cut_200": 0.5035900223567,
        "ndcg_cut_500": 0.5035900223567,
        "ndcg_cut_1000": 0.5035900223567,
        "success_1": 1.0,
        "success_5": 1.0,
        "success_10": 1.0,
        "count_relevant_top5": 1
    },
    "T18Eval-00037": {
        "map": 0.30573269564612066,
        "recip_rank": 1.0,
        "ndcg_cut_5": 0.5968814958455909,
        "ndcg_cut_10": 0.486362007892271,
        "ndcg_cut_15": 0.44958301063086126,
        "ndcg_cut_20": 0.5149372023367886,
        "ndcg_cut_30": 0.5149372023367886,
        "ndcg_cut_100": 0.5884255588060839,
        "ndcg_cut_200": 0.6262859739584451,
        "ndcg_cut_500": 0.6346536274638471,
        "ndcg_cut_1000": 0.6346536274638471,
        "success_1": 1.0,
        "success_5": 1.0,
        "success_10": 1.0,
        "count_relevant_top5": 3
    },
    "T18Eval-00038": {
        "map": 0.057745135588290294,
        "recip_rank": 0.25,
        "ndcg_cut_5": 0.14606834984270645,
        "ndcg_cut_10": 0.11838279295536291,
        "ndcg_cut_15": 0.11838279295536291,
        "ndcg_cut_20": 0.11838279295536291,
        "ndcg_cut_30": 0.11838279295536291,
        "ndcg_cut_100": 0.21381889276151628,
        "ndcg_cut_200": 0.21381889276151628,
        "ndcg_cut_500": 0.31462061089323506,
        "ndcg_cut_1000": 0.34485086214203103,
        "success_1": 0.0,
        "success_5": 1.0,
        "success_10": 1.0,
        "count_relevant_top5": 1
    },
    "T18Eval-00039": {
        "map": 0.25,
        "recip_rank": 0.5,
        "ndcg_cut_5": 0.17376534287144002,
        "ndcg_cut_10": 0.17376534287144002,
        "ndcg_cut_15": 0.17376534287144002,
        "ndcg_cut_20": 0.17376534287144002,
        "ndcg_cut_30": 0.17376534287144002,
        "ndcg_cut_100": 0.17376534287144002,
        "ndcg_cut_200": 0.17376534287144002,
        "ndcg_cut_500": 0.17376534287144002,
        "ndcg_cut_1000": 0.17376534287144002,
        "success_1": 0.0,
        "success_5": 1.0,
        "success_10": 1.0,
        "count_relevant_top5": 1
    },
    "T18Eval-00040": {
        "map": 0.4085576259489303,
        "recip_rank": 1.0,
        "ndcg_cut_5": 0.5562983930884396,
        "ndcg_cut_10": 0.5562983930884396,
        "ndcg_cut_15": 0.5562983930884396,
        "ndcg_cut_20": 0.5562983930884396,
        "ndcg_cut_30": 0.7192116199364307,
        "ndcg_cut_100": 0.7192116199364307,
        "ndcg_cut_200": 0.7192116199364307,
        "ndcg_cut_500": 0.7192116199364307,
        "ndcg_cut_1000": 0.7192116199364307,
        "success_1": 1.0,
        "success_5": 1.0,
        "success_10": 1.0,
        "count_relevant_top5": 1
    },
    "T18Eval-00041": {
        "map": 0.17500000000000002,
        "recip_rank": 0.25,
        "ndcg_cut_5": 0.20210734650054762,
        "ndcg_cut_10": 0.20210734650054762,
        "ndcg_cut_15": 0.20210734650054762,
        "ndcg_cut_20": 0.42375744548835564,
        "ndcg_cut_30": 0.42375744548835564,
        "ndcg_cut_100": 0.42375744548835564,
        "ndcg_cut_200": 0.42375744548835564,
        "ndcg_cut_500": 0.42375744548835564,
        "ndcg_cut_1000": 0.42375744548835564,
        "success_1": 0.0,
        "success_5": 1.0,
        "success_10": 1.0,
        "count_relevant_top5": 1
    },
    "T18Eval-00042": {
        "map": 0.01116169482049439,
        "recip_rank": 0.029411764705882353,
        "ndcg_cut_5": 0.0,
        "ndcg_cut_10": 0.0,
        "ndcg_cut_15": 0.0,
        "ndcg_cut_20": 0.0,
        "ndcg_cut_30": 0.0,
        "ndcg_cut_100": 0.09149012142095872,
        "ndcg_cut_200": 0.09149012142095872,
        "ndcg_cut_500": 0.14396738894370836,
        "ndcg_cut_1000": 0.14396738894370836,
        "success_1": 0.0,
        "success_5": 0.0,
        "success_10": 0.0,
        "count_relevant_top5": 0
    },
    "T18Eval-00043": {
        "map": 0.0,
        "recip_rank": 0.0,
        "ndcg_cut_5": 0.0,
        "ndcg_cut_10": 0.0,
        "ndcg_cut_15": 0.0,
        "ndcg_cut_20": 0.0,
        "ndcg_cut_30": 0.0,
        "ndcg_cut_100": 0.0,
        "ndcg_cut_200": 0.0,
        "ndcg_cut_500": 0.0,
        "ndcg_cut_1000": 0.0,
        "success_1": 0.0,
        "success_5": 0.0,
        "success_10": 0.0,
        "count_relevant_top5": 0
    },
    "T18Eval-00044": {
        "map": 0.10992749036773371,
        "recip_rank": 1.0,
        "ndcg_cut_5": 0.48306700197788277,
        "ndcg_cut_10": 0.3843483686763149,
        "ndcg_cut_15": 0.3594068143027296,
        "ndcg_cut_20": 0.3579767402901281,
        "ndcg_cut_30": 0.3793430128486714,
        "ndcg_cut_100": 0.4465117215031314,
        "ndcg_cut_200": 0.4465117215031314,
        "ndcg_cut_500": 0.5038540107706652,
        "ndcg_cut_1000": 0.5038540107706652,
        "success_1": 1.0,
        "success_5": 1.0,
        "success_10": 1.0,
        "count_relevant_top5": 1
    },
    "T18Eval-00045": {
        "map": 0.02429876060013046,
        "recip_rank": 0.16666666666666666,
        "ndcg_cut_5": 0.0,
        "ndcg_cut_10": 0.11207454275960439,
        "ndcg_cut_15": 0.11207454275960439,
        "ndcg_cut_20": 0.11207454275960439,
        "ndcg_cut_30": 0.11207454275960439,
        "ndcg_cut_100": 0.11207454275960439,
        "ndcg_cut_200": 0.11207454275960439,
        "ndcg_cut_500": 0.11207454275960439,
        "ndcg_cut_1000": 0.146302457992921,
        "success_1": 0.0,
        "success_5": 0.0,
        "success_10": 1.0,
        "count_relevant_top5": 0
    }
}